product.recaptcha_invisible-2.0-py3.11-nspkg.pth
product/recaptcha_invisible/__init__.py
product/recaptcha_invisible/configure.zcml
product/recaptcha_invisible/controlpanel.py
product/recaptcha_invisible/controlpanel.zcml
product/recaptcha_invisible/field.py
product/recaptcha_invisible/field.zcml
product/recaptcha_invisible/interfaces.py
product/recaptcha_invisible/permissions.zcml
product/recaptcha_invisible/setuphandlers.py
product/recaptcha_invisible/testing.py
product/recaptcha_invisible/validator.py
product/recaptcha_invisible/widget.py
product/recaptcha_invisible/widget.zcml
product/recaptcha_invisible/widget_display.pt
product/recaptcha_invisible/widget_input.pt
product/recaptcha_invisible/browser/__init__.py
product/recaptcha_invisible/browser/configure.zcml
product/recaptcha_invisible/browser/verify.py
product/recaptcha_invisible/browser/overrides/.gitkeep
product/recaptcha_invisible/browser/static/.gitkeep
product/recaptcha_invisible/locales/README.rst
product/recaptcha_invisible/locales/__init__.py
product/recaptcha_invisible/locales/compile.sh
product/recaptcha_invisible/locales/manual.pot
product/recaptcha_invisible/locales/product.recaptcha_invisible.pot
product/recaptcha_invisible/locales/update.sh
product/recaptcha_invisible/locales/ca/LC_MESSAGES/product.recaptcha_invisible.mo
product/recaptcha_invisible/locales/ca/LC_MESSAGES/product.recaptcha_invisible.po
product/recaptcha_invisible/locales/en/LC_MESSAGES/product.recaptcha_invisible.mo
product/recaptcha_invisible/locales/en/LC_MESSAGES/product.recaptcha_invisible.po
product/recaptcha_invisible/locales/es/LC_MESSAGES/product.recaptcha_invisible.mo
product/recaptcha_invisible/locales/es/LC_MESSAGES/product.recaptcha_invisible.po
product/recaptcha_invisible/profiles/default/browserlayer.xml
product/recaptcha_invisible/profiles/default/controlpanel.xml
product/recaptcha_invisible/profiles/default/metadata.xml
product/recaptcha_invisible/profiles/default/registry.xml
product.recaptcha_invisible-2.0.dist-info/LICENSE.GPL
product.recaptcha_invisible-2.0.dist-info/LICENSE.rst
product.recaptcha_invisible-2.0.dist-info/METADATA
product.recaptcha_invisible-2.0.dist-info/WHEEL
product.recaptcha_invisible-2.0.dist-info/entry_points.txt
product.recaptcha_invisible-2.0.dist-info/namespace_packages.txt
product.recaptcha_invisible-2.0.dist-info/top_level.txt
product.recaptcha_invisible-2.0.dist-info/RECORD
